simpleaudiohamiltoncs-1.1.0.dist-info/RECORD
simpleaudiohamiltoncs-1.1.0.dist-info/WHEEL
simpleaudiohamiltoncs-1.1.0.dist-info/top_level.txt
simpleaudiohamiltoncs-1.1.0.dist-info/METADATA
simpleaudiohamiltoncs-1.1.0.dist-info/licenses/LICENSE.txt
simpleaudiohamiltoncs/functionchecks.py
simpleaudiohamiltoncs/__init__.py
simpleaudiohamiltoncs/_simpleaudiohamiltoncs.cpython-310-darwin.so
simpleaudiohamiltoncs/shiny.py
simpleaudiohamiltoncs/test_audio/c.wav
simpleaudiohamiltoncs/test_audio/g.wav
simpleaudiohamiltoncs/test_audio/e.wav
simpleaudiohamiltoncs/test_audio/notes_2_16_44.wav
simpleaudiohamiltoncs/test_audio/left_right.wav
