Metadata-Version: 2.4
Name: simpleaudiohamiltoncs
Version: 1.1.0
Summary: Simple, asynchronous audio playback for Python 3.
Home-page: https://github.com/hamilton-cs/py-simple-audio/
Author: Joe Hamilton, Charles Beard, Lulu Ceccon
Author-email: hdong@hamilton.edu
License: MIT
Keywords: audio,wave,media,multimedia,sound,alsa,coreaudio,winmm,music
Classifier: Programming Language :: Python :: 3.10
Classifier: Programming Language :: Python :: 3.11
Classifier: Programming Language :: Python :: 3.12
Classifier: Topic :: Multimedia :: Sound/Audio
Classifier: Operating System :: POSIX :: Linux
Classifier: Operating System :: Microsoft :: Windows
Classifier: Operating System :: MacOS :: MacOS X
License-File: LICENSE.txt
Dynamic: author
Dynamic: author-email
Dynamic: classifier
Dynamic: description
Dynamic: description-content-type
Dynamic: home-page
Dynamic: keywords
Dynamic: license
Dynamic: license-file
Dynamic: summary
